gtfast/_Messages.py
gtfast/__init__.py
gtfast/_add_GTF_annotations_to_adata.py
gtfast/_cache_parsed_filepaths.py
gtfast/_create_gtf_csv_dir.py
gtfast/_filter_gtf_df.py
gtfast/_gtfparse.py
gtfast/_parse_GTF_to_csv.py
gtfast/_read_GTF_csv.py
gtfast/_write_GTF_csv.py
GTFast-0.0.3.dist-info/LICENSE
GTFast-0.0.3.dist-info/METADATA
GTFast-0.0.3.dist-info/WHEEL
GTFast-0.0.3.dist-info/top_level.txt
GTFast-0.0.3.dist-info/RECORD
