Metadata-Version: 2.1
Name: GTFast
Version: 0.0.3
Summary: GTFast - cache and subset a `.gtf` file as a `.csv` for faster subsequent use.
Home-page: https://github.com/mvinyard/GTFast
Author: Michael E. Vinyard - Harvard University - Massachussetts General Hospital - Broad Institute of MIT and Harvard
Author-email: mvinyard@broadinstitute.org
License: MIT
Platform: UNKNOWN
Classifier: Development Status :: 2 - Pre-Alpha
Classifier: Programming Language :: Python :: 3.6
Classifier: Intended Audience :: Science/Research
Classifier: Topic :: Scientific/Engineering :: Bio-Informatics
Requires-Python: >3.6.0
License-File: LICENSE
Requires-Dist: gtfparse (>=1.2.1)
Requires-Dist: pandas (>=1.3.5)
Requires-Dist: pydk (>=0.0.4)
